serialx/__init__.py
serialx/async_serial.py
serialx/common.py
serialx/descriptor_transport.py
serialx/platforms/__init__.py
serialx/platforms/serial_darwin.py
serialx/platforms/serial_posix.py
serialx/platforms/serial_win32.py
serialx/tools/__init__.py
serialx/tools/list_ports.py
serialx/tools/list_ports_common.py
src/darwin.rs
src/lib.rs
src/windows.rs
serialx-0.6.2.dist-info/METADATA
serialx-0.6.2.dist-info/WHEEL
serialx-0.6.2.dist-info/top_level.txt
serialx-0.6.2.dist-info/RECORD
