Metadata-Version: 2.4
Name: serialx
Version: 0.6.2
Summary: Serial library with native async support for Windows and POSIX
Author-email: puddly <puddly3@gmail.com>
License-Expression: Apache-2.0
Project-URL: repository, https://github.com/puddly/serialx
Requires-Python: >=3.10
Requires-Dist: typing-extensions
Requires-Dist: async-timeout; python_version < "3.12"
Requires-Dist: pywin32; platform_system == "Windows"
Provides-Extra: dev
Requires-Dist: ruff; extra == "dev"
Requires-Dist: pytest; extra == "dev"
Requires-Dist: pre-commit; extra == "dev"
Requires-Dist: pytest-asyncio; extra == "dev"
Requires-Dist: pytest-timeout; extra == "dev"
Requires-Dist: pytest-xdist; extra == "dev"
